odoo/addons/maintenance_team_hierarchy/README.rst
odoo/addons/maintenance_team_hierarchy/__init__.py
odoo/addons/maintenance_team_hierarchy/__manifest__.py
odoo/addons/maintenance_team_hierarchy/i18n/es.po
odoo/addons/maintenance_team_hierarchy/i18n/it.po
odoo/addons/maintenance_team_hierarchy/i18n/maintenance_team_hierarchy.pot
odoo/addons/maintenance_team_hierarchy/i18n/pt_BR.po
odoo/addons/maintenance_team_hierarchy/models/__init__.py
odoo/addons/maintenance_team_hierarchy/models/maintenance_team.py
odoo/addons/maintenance_team_hierarchy/readme/CONTRIBUTORS.rst
odoo/addons/maintenance_team_hierarchy/readme/DESCRIPTION.rst
odoo/addons/maintenance_team_hierarchy/static/description/icon.png
odoo/addons/maintenance_team_hierarchy/static/description/index.html
odoo/addons/maintenance_team_hierarchy/tests/__init__.py
odoo/addons/maintenance_team_hierarchy/tests/test_team_hierarchy.py
odoo/addons/maintenance_team_hierarchy/views/maintenance_team.xml
odoo12_addon_maintenance_team_hierarchy-12.0.1.0.0.99.dev13.dist-info/METADATA
odoo12_addon_maintenance_team_hierarchy-12.0.1.0.0.99.dev13.dist-info/WHEEL
odoo12_addon_maintenance_team_hierarchy-12.0.1.0.0.99.dev13.dist-info/top_level.txt
odoo12_addon_maintenance_team_hierarchy-12.0.1.0.0.99.dev13.dist-info/RECORD
